safefunc.py
safefunc-0.0.5.post1.dist-info/METADATA
safefunc-0.0.5.post1.dist-info/WHEEL
safefunc-0.0.5.post1.dist-info/top_level.txt
safefunc-0.0.5.post1.dist-info/RECORD
