Metadata-Version: 2.1
Name: safefunc
Version: 0.0.5.post1
Summary: Make sudden erros not stop your program
Author: phoenixR
License: MIT
Classifier: Development Status :: 7 - Inactive
